setup.py
bin/imap-filter-client
imap_filter_client/__init__.py
imap_filter_client/config.py
imap_filter_client/filter_process.py
imap_filter_client/imap_listener.py
imap_filter_client/imap_server.py
imap_filter_client/imap_server_pool.py
imap_filter_client/message.py
imap_filter_client/message_processor.py
imap_filter_client/passwd.py
imap_filter_client/spam_filters.py
imap_filter_client.egg-info/PKG-INFO
imap_filter_client.egg-info/SOURCES.txt
imap_filter_client.egg-info/dependency_links.txt
imap_filter_client.egg-info/requires.txt
imap_filter_client.egg-info/top_level.txt