Metadata-Version: 1.0
Name: imap-filter-client
Version: 1.0.0
Summary: Small python IMAP client daemon for filtering email messages
Home-page: https://github.com/voidpp/imap-filter-client
Author: Lajos Santa
Author-email: santa.lajos@coldline.hu
License: UNKNOWN
Platform: UNKNOWN
